Workbook

Sheet Transactions 
A1: Date | B1: Type | C1: Category | D1: Description | E1: Payment Mode | F1: Amount
A2: 46296 | B2: Income | C2: Allowance | D2: Monthly Allowance | E2: UPI | F2: 25000
A3: 46296 | B3: Expense | C3: Food | D3: Mess & Meals | E3: UPI | F3: 4200
A4: 46297 | B4: Expense | C4: Travel | D4: Auto/Local Travel | E4: UPI | F4: 800
A5: 46298 | B5: Expense | C5: Education | D5: Books & Study Material | E5: UPI | F5: 1500
A6: 46299 | B6: Expense | C6: Gym/Fitness | D6: Gym & Supplements | E6: UPI | F6: 2500
A7: 46300 | B7: Expense | C7: Shopping | D7: Clothes & Personal Items | E7: Card | F7: 1800
A8: 46301 | B8: Expense | C8: Entertainment | D8: Movies & Outings | E8: UPI | F8: 1000
A9: 46303 | B9: Expense | C9: Food | D9: Snacks & Eating Out | E9: UPI | F9: 1200
A10: 46305 | B10: Expense | C10: Travel | D10: Cab/Auto | E10: UPI | F10: 600
A11: 46307 | B11: Expense | C11: Education | D11: Course/Study Material | E11: Card | F11: 1000
A12: 46310 | B12: Expense | C12: Food | D12: Eating Out | E12: UPI | F12: 900
A13: 46313 | B13: Expense | C13: Gym/Fitness | D13: Fitness Expenses | E13: UPI | F13: 1200
... A16: 46320 | B16: Expense | C16: Food | D16: Meals & Snacks | E16: UPI | F16: 1100

Sheet Budget Vs Actual
A1: Category | B1: Budget | C1: Actual | D1: Variance | E1: Status
A2: Food | B2: 6000 | C2: =SUMIFS(ExpenseTable[Amount],ExpenseTable[Category],A2,ExpenseTable[Type],"Expense") -> 7400 | D2: =B2-C2 -> -1400 | E2: =IF(D2<0,"Over Budget","Under Budget") -> Over Budget
A3: Travel | B3: 2000 | C3: =SUMIFS(ExpenseTable[Amount],ExpenseTable[Category],A3,ExpenseTable[Type],"Expense") -> 1400 | D3: =B3-C3 -> 600 | E3: =IF(D3<0,"Over Budget","Under Budget") -> Under Budget
A4: Education | B4: 3000 | C4: =SUMIFS(ExpenseTable[Amount],ExpenseTable[Category],A4,ExpenseTable[Type],"Expense") -> 2500 | D4: =B4-C4 -> 500 | E4: =IF(D4<0,"Over Budget","Under Budget") -> Under Budget
A5: Gym/Fitness | B5: 4000 | C5: =SUMIFS(ExpenseTable[Amount],ExpenseTable[Category],A5,ExpenseTable[Type],"Expense") -> 3700 | D5: =B5-C5 -> 300 | E5: =IF(D5<0,"Over Budget","Under Budget") -> Under Budget
A6: Shopping | B6: 3000 | C6: =SUMIFS(ExpenseTable[Amount],ExpenseTable[Category],A6,ExpenseTable[Type],"Expense") -> 2500 | D6: =B6-C6 -> 500 | E6: =IF(D6<0,"Over Budget","Under Budget") -> Under Budget
A7: Entertainment | B7: 2000 | C7: =SUMIFS(ExpenseTable[Amount],ExpenseTable[Category],A7,ExpenseTable[Type],"Expense") -> 1800 | D7: =B7-C7 -> 200 | E7: =IF(D7<0,"Over Budget","Under Budget") -> Under Budget
A8: Other | B8: 1000 | C8: =SUMIFS(ExpenseTable[Amount],ExpenseTable[Category],A8,ExpenseTable[Type],"Expense") -> 0 | D8: =B8-C8 -> 1000 | E8: =IF(D8<0,"Over Budget","Under Budget") -> Under Budget

Sheet Analysis
A1: Financial Metric | B1: Value
A2: Total Income | B2: =SUMIFS(ExpenseTable[Amount],ExpenseTable[Type],"Income") -> 25000
A3: Total Expenses | B3: =SUMIFS(ExpenseTable[Amount],ExpenseTable[Type],"Expense") -> 19300
A4: Net Savings | B4: =B2-B3 -> 5700
A5: Savings Rate | B5: =B4/B2 -> 0.228
A6: Highest Spending Category | B6: =INDEX('Budget Vs Actual'!A2:A8, MATCH(MAX('Budget Vs Actual'!C2:C8), 'Budget Vs Actual'!C2:C8, 0)) -> Food
A7: Largest Expense | B7: =_xlfn.MAXIFS(ExpenseTable[Amount],ExpenseTable[Type],"Expense") -> 4200

Sheet Dashboard
A1: PERSONAL EXPENSE & BUDGET ANALYZER
A2: Monthly Financial Summary | Excel-Based Financial Analysis
A4: Total Income | C4: Total Expenses | E4: Net Savings | G4: Savings Rate
A5: =Analysis!B2 -> 25000 | C5: =Analysis!B3 -> 19300 | E5: =Analysis!B4 -> 5700 | G5: =Analysis!B5 -> 0.228
